openai_kernel/__init__.py
openai_kernel/__main__.py
openai_kernel/kernel.json
openai_kernel/kernel.py
openai_kernel/mock_kernel.py
openai_kernel/outputs.py
openai_kernel/utils.py
openai_kernel/version.py
openai_kernel/magics/__init__.py
openai_kernel/magics/clear_history_magic.py
openai_kernel/magics/history_magic.py
openai_kernel/magics/mode_magic.py
openai_kernel/magics/openai_api_magic.py
openai_kernel/magics/set_magic.py
openai_kernel-0.0.3.dist-info/METADATA
openai_kernel-0.0.3.dist-info/WHEEL
openai_kernel-0.0.3.dist-info/top_level.txt
openai_kernel-0.0.3.dist-info/RECORD
