Metadata-Version: 2.1
Name: openai-kernel
Version: 0.0.3
Summary: OpenAI jupyter kernel
Home-page: https://github.com/OakCityLabs/openai_kernel
Author: Oak City Labs
Author-email: team@oakcity.io
Classifier: Programming Language :: Python :: 3
Classifier: License :: OSI Approved :: MIT License
Classifier: Operating System :: OS Independent
Requires-Python: >=3
Requires-Dist: openai (<1,>=0.27.4)
Requires-Dist: metakernel (<1,>=0.29.4)
